storage/__init__.py
storage/base.py
storage/conf.py
storage/exceptions.py
storage/handler.py
storage/utils.py
storage/backends/__init__.py
storage/backends/filesystem.py
storage/backends/s3.py
storage/files/__init__.py
storage/files/base.py
storage/files/images.py
storage/files/locks.py
storage/files/move.py
storage/files/temp.py
storage/files/utils.py
tests/__init__.py
tests/test_storage.py
tests/test_storage_handler.py
python_file_storage-0.3.0.dist-info/LICENSE
python_file_storage-0.3.0.dist-info/METADATA
python_file_storage-0.3.0.dist-info/WHEEL
python_file_storage-0.3.0.dist-info/top_level.txt
python_file_storage-0.3.0.dist-info/RECORD
