Metadata-Version: 2.1
Name: python-file-storage
Version: 0.3.0
Summary: A Python package that exposes a consistent API for working with different storage backends.
Author: Armandt van Zyl
Classifier: Environment :: Web Environment
Classifier: Intended Audience :: Developers
Classifier: Topic :: Internet :: WWW/HTTP
Classifier: Programming Language :: Python
Classifier: Programming Language :: Python :: 3
Classifier: Programming Language :: Python :: 3.8
Classifier: Programming Language :: Python :: 3 :: Only
Classifier: License :: OSI Approved :: MIT License
Requires-Python: >=3.8
License-File: LICENSE
Provides-Extra: boto3
Requires-Dist: boto3; extra == "boto3"
